setup.cfg
setup.py
netception/__init__.py
netception/inceptor.py
netception/metadata.py
netception.egg-info/PKG-INFO
netception.egg-info/SOURCES.txt
netception.egg-info/dependency_links.txt
netception.egg-info/top_level.txt
netception/utils/__init__.py
netception/utils/visualization_util.py
tests/__init__.py
tests/test_inceptor.py
tests/utils/__init__.py
tests/utils/test_visualization_util.py