Metadata-Version: 1.1
Name: netception
Version: 0.2.0
Summary: A neural network inception library
Home-page: https://github.com/PhTrempe/netception
Author: Philippe Trempe
Author-email: ph.trempe@gmail.com
License: MIT
Download-URL: https://github.com/PhTrempe/netception/archive/0.2.0.tar.gz
Keywords: neural,network,inception,machine,learning
Platform: UNKNOWN
Requires: numpy
Requires: keras
